MANIFEST.in
README.rst
requirements.txt
setup.cfg
setup.py
lisa/__init__.py
lisa/plugins/__init__.py
lisa/plugins/Domoticz/__init__.py
lisa/plugins/Domoticz/domoticz.json
lisa/plugins/Domoticz/lang/en/LC_MESSAGES/domoticz.mo
lisa/plugins/Domoticz/lang/en/LC_MESSAGES/domoticz.po
lisa/plugins/Domoticz/lang/fr/LC_MESSAGES/domoticz.mo
lisa/plugins/Domoticz/lang/fr/LC_MESSAGES/domoticz.po
lisa/plugins/Domoticz/modules/__init__.py
lisa/plugins/Domoticz/modules/domoticz.py
lisa/plugins/Domoticz/web/__init__.py
lisa/plugins/Domoticz/web/api.py
lisa/plugins/Domoticz/web/models.py
lisa/plugins/Domoticz/web/tests.py
lisa/plugins/Domoticz/web/urls.py
lisa/plugins/Domoticz/web/views.py
lisa_plugin_Domoticz.egg-info/PKG-INFO
lisa_plugin_Domoticz.egg-info/SOURCES.txt
lisa_plugin_Domoticz.egg-info/dependency_links.txt
lisa_plugin_Domoticz.egg-info/namespace_packages.txt
lisa_plugin_Domoticz.egg-info/requires.txt
lisa_plugin_Domoticz.egg-info/top_level.txt